hhportfolio/__init__.py
hhportfolio/deprecate.py
hhportfolio/periods.py
hhportfolio/portfoliobacktest.py
hhportfolio/stats.py
hhportfolio/timeseries.py
hhportfolio/utils.py
hhportfolio-0.27.dist-info/METADATA
hhportfolio-0.27.dist-info/WHEEL
hhportfolio-0.27.dist-info/top_level.txt
hhportfolio-0.27.dist-info/RECORD
